lunarispackage/__init__.py
lunarispackage-0.1.dist-info/METADATA
lunarispackage-0.1.dist-info/WHEEL
lunarispackage-0.1.dist-info/top_level.txt
lunarispackage-0.1.dist-info/RECORD
