Metadata-Version: 2.4
Name: lunarispackage
Version: 0.1
Summary: This is Speech to Text Package created by WhizzyWhiznerd
Author: WhizzyWhiznerd
Author-email: example@gmail.com
Dynamic: author
Dynamic: author-email
Dynamic: summary
